MANIFEST.in
setup.py
Flask_Personal_Access_Token.egg-info/PKG-INFO
Flask_Personal_Access_Token.egg-info/SOURCES.txt
Flask_Personal_Access_Token.egg-info/dependency_links.txt
Flask_Personal_Access_Token.egg-info/not-zip-safe
Flask_Personal_Access_Token.egg-info/requires.txt
Flask_Personal_Access_Token.egg-info/top_level.txt
flask_personal_access_token/__init__.py
flask_personal_access_token/admin.py
flask_personal_access_token/api.py
flask_personal_access_token/app.py
flask_personal_access_token/core.py
flask_personal_access_token/model.py
flask_personal_access_token/web.py
flask_personal_access_token/static/admin.js
flask_personal_access_token/static/ng-admin.min.css
flask_personal_access_token/static/ng-admin.min.js
flask_personal_access_token/templates/personal_access_token/index.html
flask_personal_access_token/templates/personal_access_token/login.html