Metadata-Version: 1.1
Name: Flask-Personal-Access-Token
Version: 0.1.1
Summary: Flask Personal Access Token Management Extension
Home-page: https://github.com/soasme/flask-personal-access-token
Author: Ju Lin
Author-email: soasme@gmail.com
License: MIT
Platform: any
Classifier: Framework :: Flask
Classifier: Natural Language :: English
Classifier: Environment :: Web Environment
Classifier: Intended Audience :: Developers
Classifier: License :: OSI Approved :: MIT License
Classifier: Operating System :: OS Independent
Classifier: Programming Language :: Python
Classifier: Topic :: Internet :: WWW/HTTP :: Dynamic Content
Classifier: Topic :: Software Development :: Libraries :: Python Modules
